adwite/__init__.py
adwite/__main__.py
adwite/cefweb.py
adwite-0.3.dist-info/METADATA
adwite-0.3.dist-info/WHEEL
adwite-0.3.dist-info/top_level.txt
adwite-0.3.dist-info/RECORD
