Metadata-Version: 2.1
Name: adwite
Version: 0.3
Summary: GUI extension library
Home-page: https://adwite.netlify.app
Author: XiangQinxi
Author-email: XiangQinxi@outlook.com
Classifier: Programming Language :: Python :: 3
Classifier: License :: OSI Approved :: MIT License
Classifier: Operating System :: OS Independent
Requires-Python: >=3
